[
  {
    "user": {
      "name": "Newton",
      "avatars": "https://i.imgur.com/73hZDYK.png"
      ,
      "handle": "@SirIsaac"
    },
    "content": {
      "text": "I lost a leg today but it's okay, I still have one left."  
    },
    "created_at": 1461116232227
  },
  {
    "user": {
      "name": "Descartes",
      "avatars": "https://i.imgur.com/nlhLi3I.png",
      "handle": "@rd" },
    "content": {
      "text": "Heute, habe ich mein bein verloren. Es ist schon okay, Ich habe noch ein mehr."
    },
    "created_at": 1461113959088
  }
]
